__init__.py
src/privateai_client/__init__.py
src/privateai_client/objects.py
src/privateai_client/pai_client.py
src/privateai_client/components/__init__.py
src/privateai_client/components/pai_requests.py
src/privateai_client/components/pai_responses.py
src/privateai_client/components/pai_uris.py
src/privateai_client/components/request_objects.py
privateai-1.3.1.dist-info/METADATA
privateai-1.3.1.dist-info/WHEEL
privateai-1.3.1.dist-info/licenses/LICENSE
privateai-1.3.1.dist-info/RECORD
