Metadata-Version: 2.1
Name: privateai
Version: 1.3.1
Summary: A thin client for communicating with the Private AI de-identication API.
Project-URL: Homepage, https://github.com/privateai/pai-thin-client/
Project-URL: Bug Tracker, https://github.com/privateai/pai-thin-client/issues
Author-email: Adam Guiducci <adam.guiducci@private-ai.com>, Bryan Bell-Smith <bryan.bellsmith@private-ai.com>
License-File: LICENSE
Classifier: License :: OSI Approved :: MIT License
Classifier: Operating System :: OS Independent
Classifier: Programming Language :: Python :: 3
Requires-Python: >=3.8
